.gitignore
AUTHORS.rst
CHANGELOG.rst
LICENSE
MANIFEST.in
README.rst
pyproject.toml
.github/workflows/python-package.yml
docs/api.rst
docs/authors.rst
docs/changelog.rst
docs/conf.py
docs/index.rst
docs/installation.rst
docs/readme.rst
johannesmann/__init__.py
johannesmann/johannesmann.py
johannesmann.egg-info/PKG-INFO
johannesmann.egg-info/SOURCES.txt
johannesmann.egg-info/dependency_links.txt
johannesmann.egg-info/requires.txt
johannesmann.egg-info/top_level.txt
tests/test_johannesmann.py