Metadata-Version: 2.1
Name: johannesmann
Version: 0.1.0
Summary: Python implementation of the Johannesmann Spatial Tessellation method.
Author-email: Leander Claes <claes@emt.uni-paderborn.de>
License: BSD license
Project-URL: homepage, https://emt.uni-paderborn.de
Classifier: Development Status :: 2 - Pre-Alpha
Classifier: Intended Audience :: Science/Research
Classifier: License :: OSI Approved :: BSD License
Classifier: Programming Language :: Python :: 3
Classifier: Topic :: Scientific/Engineering
Requires-Python: >=3.7
License-File: LICENSE
License-File: AUTHORS.rst
Requires-Dist: numpy
Provides-Extra: doc
Requires-Dist: setuptools_scm; extra == "doc"
Requires-Dist: sphinx; extra == "doc"
Requires-Dist: sphinx-rtd-theme; extra == "doc"
Provides-Extra: test
Requires-Dist: pytest; extra == "test"
